README
setup.cfg
setup.py
govenv/__init__.py
govenv/gopath.py
govenv.egg-info/PKG-INFO
govenv.egg-info/SOURCES.txt
govenv.egg-info/dependency_links.txt
govenv.egg-info/entry_points.txt
govenv.egg-info/top_level.txt