Metadata-Version: 1.0
Name: govenv
Version: 0.2.1
Summary: Golang Enhancements to virtualenv
Home-page: https://github.com/termie/govenv
Author: Andy Smith
Author-email: github@anarkystic.com
License: UNKNOWN
Platform: UNKNOWN
